yara.cp39-win_amd64.pyd
yara_python_dex-1.0.7.dist-info/LICENSE
yara_python_dex-1.0.7.dist-info/METADATA
yara_python_dex-1.0.7.dist-info/WHEEL
yara_python_dex-1.0.7.dist-info/top_level.txt
yara_python_dex-1.0.7.dist-info/RECORD
