Metadata-Version: 2.1
Name: yara-python-dex
Version: 1.0.7
Summary: Python interface for YARA
Home-page: https://github.com/MobSF/yara-python-dex
Author: Victor M. Alvarez
Author-email: plusvic@gmail.com, vmalvarez@virustotal.com
License: Apache 2.0
Classifier: Programming Language :: Python
Classifier: License :: OSI Approved :: Apache Software License
Classifier: Operating System :: OS Independent
Classifier: Development Status :: 5 - Production/Stable
License-File: LICENSE
